<!-- xml reconstructed by ValveResourceFormat: https://vrf.steamdb.info/ -->
<root>
	<styles>
		<include src="s2r://panorama/styles/dotastyles.vcss_c" />
		<include src="s2r://panorama/styles/dashboard_page_shared.vcss_c" />
		<include src="s2r://panorama/styles/leaf_pages/dashboard_page_debut_styles.vcss_c" />
		<include src="s2r://panorama/styles/leaf_pages/dashboard_page_debut_outlanders.vcss_c" />
	</styles>
	<scripts>
		<include src="s2r://panorama/scripts/util.vts_c" />
		<include src="s2r://panorama/scripts/sequence_actions.vts_c" />
		<include src="s2r://panorama/scripts/leaf_pages/dashboard_page_debut_outlanders.vjs_c" />
	</scripts>
	<DOTAReferencePage class="DashboardPage" onpagesetupsuccess="RunPageAnimation()" oncancel="DOTASetCurrentDashboardPageFullscreen( false )">
		<MoviePanel id="Outlanders" src="file://{resources}/videos/promo/outlanders_bg.webm" repeat="true" autoplay="onload" />
		<Panel id="TitleContainer" hittest="false" hittestchildren="false">
			<Label id="TitleMain" />
		</Panel>
	</DOTAReferencePage>
</root>
