<!-- xml reconstructed by ValveResourceFormat: https://vrf.steamdb.info/ -->
<root>
	<styles>
		<include src="s2r://panorama/styles/dotastyles.vcss_c" />
		<include src="s2r://panorama/styles/dashboard_page_shared.vcss_c" />
		<include src="s2r://panorama/styles/leaf_pages/dashboard_page_debut_styles.vcss_c" />
		<include src="s2r://panorama/styles/leaf_pages/dashboard_page_debut_antimage_persona.vcss_c" />
	</styles>
	<scripts>
		<include src="s2r://panorama/scripts/util.vts_c" />
		<include src="s2r://panorama/scripts/sequence_actions.vts_c" />
		<include src="s2r://panorama/scripts/leaf_pages/dashboard_page_debut_antimage_persona.vjs_c" />
	</scripts>
	<snippets>
		<snippet name="ModelSnippet">
			<Panel>
				<DOTAScenePanel id="AMModelBackground" map="backgrounds/hero_showcase_antimage_persona" camera="herocamera" light="light_hero" renderdeferred="true" renderwaterreflections="true" rotateonhover="true" rotateonmousemove="true" antialias="true" particleonly="false" />
			</Panel>
		</snippet>
	</snippets>
	<DOTAReferencePage class="DashboardPage" onnavigatedto="RunPageAnimation()" onnavigatedaway="closeFemaleAntimageDebutPage()" oncancel="DOTASetCurrentDashboardPageFullscreen( false )">
		<Panel id="MainContainer">
			<Panel id="ModelContainer" />
			<Panel id="BottomGradient" hittest="false" />
			<Panel id="DebutInformation" hittest="false">
				<Image id="InformationBodyBackground" src="s2r://panorama/images/compendium/international2020/wriath_king_arcana/crown-main_png.vtex" hittest="false" />
				<Panel id="InformationBody" class="TopBottomFlow" hittest="false">
					<Panel id="TitleContainer" hittest="false">
						<Panel class="Title" hittest="false" />
						<Label id="Intro" text="#Debut_AM_Wei_Persona_Intro" hittest="false" />
					</Panel>
					<Panel id="ScrollPanel" class="TopBottomFlow">
						<Label id="ItemLore" text="#Debut_AM_Wei_Persona_Lore" hittest="false" />
						<MoviePanel id="ESVideo1" src="file://{resources}/videos/promo/am_persona.webm" repeat="true" autoplay="onload" />
						<Panel class="BulletList LeftRightFlow">
							<Panel class="Bullet" />
							<Panel class="BulletDesc">
								<Label html="true" text="#Debut_AM_Wei_Persona_Feature_1_Title" />
								<Label text="#Debut_AM_Wei_Persona_Feature_1_Desc" />
							</Panel>
						</Panel>
						<Panel class="BulletList LeftRightFlow">
							<Panel class="Bullet" />
							<Panel class="BulletDesc">
								<Label html="true" text="#Debut_AM_Wei_Persona_Feature_2_Title" />
								<Label text="#Debut_AM_Wei_Persona_Feature_2_Desc" />
							</Panel>
						</Panel>
						<Panel class="BulletList LeftRightFlow">
							<Panel class="Bullet" />
							<Panel class="BulletDesc">
								<Label html="true" text="#Debut_AM_Wei_Persona_Feature_3_Title" />
								<Label text="#Debut_AM_Wei_Persona_Feature_3_Desc" />
								<Panel id="ESImages">
									<Panel id="HeroPortrait" class="InlineImage" />
									<Panel id="HeroIcons" class="InlineImage" />
									<Panel id="HeroAbilities" class="InlineImage" />
								</Panel>
							</Panel>
						</Panel>
						<Panel class="BulletList LeftRightFlow">
							<Panel class="Bullet" />
							<Panel class="BulletDesc">
								<Label html="true" text="#Debut_AM_Wei_Persona_Feature_4_Title" />
								<Label text="#Debut_AM_Wei_Persona_Feature_4_Desc" />
							</Panel>
						</Panel>
					</Panel>
					<Panel id="HeroButtons">
						<Panel id="DemoButtons">
							<DemoModeButton id="DemoHeroButton" category="#npc_dota_hero_antimage" onactivate="DOTADemoHero( npc_dota_hero_antimage, 13783 )" />
							<DOTAPurchaseBattlePassReward class="PurchaseButton FixedSize" event-id="EVENT_ID_INTERNATIONAL_2020" reward-level="305" already-claimed-text="#Debut_QueenOfPainArcana_ViewProgress" already-claimed-onactivate="DOTAShowHeroPage( 39 )" />
							<TextButton class="BattlePassButton BuyBattlePassButton" onactivate="DOTAShowBPInternational2020PurchasePage( false )" text="#DOTA_FrontPage_International2019_Buy" />
						</Panel>
					</Panel>
				</Panel>
			</Panel>
			<Button class="CloseButton" onactivate="closeFemaleAntimageDebutPage()" />
		</Panel>
	</DOTAReferencePage>
</root>
