<!-- xml reconstructed by ValveResourceFormat: https://vrf.steamdb.info/ -->
<root>
	<styles>
		<include src="s2r://panorama/styles/dotastyles.vcss_c" />
		<include src="s2r://panorama/styles/frontpage_shared.vcss_c" />
		<include src="s2r://panorama/styles/frostivus_shared.vcss_c" />
		<include src="s2r://panorama/styles/events/home_page_event_frostivus_2019.vcss_c" />
	</styles>
	<CustomLayoutPanel class="EventRootCell ActionButton" onactivate="DOTAShowFrostivus2019Page()">
		<Panel id="MainContents">
			<Panel id="Background" />
			<Panel class="EventTitle">
				<Label id="Title" />
				<Label id="Subtitle" text="#DOTA_Frostivus2019_Dates" />
			</Panel>
			<Panel id="CurrentLevelContainer">
				<Panel id="EventLevel">
					<Panel id="EventLevelBadge" />
					<Label id="EventLevelNumber" text="{d:current_level}" />
				</Panel>
				<Panel id="PurchaseAndLevels" class="TopBottomFlow">
					<Panel id="CurrentLevelInfo">
						<Label id="DailyBonusAvailable" text="#DOTA_Event_DailyBonusAvailable" />
						<Panel id="DailyBonusUsed">
							<Countdown id="DailyBonusCountdown">
								<Label class="MonoNumbersFont" text="#DOTA_Event_NextDailyBonus" />
							</Countdown>
						</Panel>
						<ProgressBar id="CurrentLevelProgress" />
						<Label class="EventLevelProgressText" text="#DOTA_EventLevelPointsProgress" />
					</Panel>
					<Panel id="EventEnded">
						<Label id="LabelEventEnded" text="#DOTA_Frostivus2019_Concluded" />
						<Label id="LabelUseConsumables" text="#DOTA_Frostivus2019_Dates_Expire" html="true" />
					</Panel>
				</Panel>
			</Panel>
		</Panel>
		<Panel id="UnclaimedRewards">
			<Label class="UnclaimedCount Singular" text="#DOTA_Home_BattlePass_Unclaimed_Singular" />
			<Label class="UnclaimedCount Plural" text="#DOTA_Home_BattlePass_Unclaimed_Plural" />
		</Panel>
	</CustomLayoutPanel>
</root>
