<!-- xml reconstructed by ValveResourceFormat: https://vrf.steamdb.info/ -->
<root>
	<styles>
		<include src="s2r://panorama/styles/dotastyles.vcss_c" />
		<include src="s2r://panorama/styles/dashboard_page_shared.vcss_c" />
		<include src="s2r://panorama/styles/battle_pass/international2022/bp_international2022_shared.vcss_c" />
		<include src="s2r://panorama/styles/battle_pass/international2022/bp_international2022_candy_shop_upcoming.vcss_c" />
	</styles>
	<DOTABPInternational2022CandyShopUpcomingPage class="DashboardPage FullDashboardPage" dashboardclass="SeasonalBattlePassPage International2022BattlePassPage International2022BPHome">
		<Panel class="PageBackground" />
		<Panel class="MainContents">
			<Panel class="TitleContainer">
				<Label class="title" text="#DOTA_International2022_CandyShop_Title" />
				<Label class="subtitle" text="#DOTA_International2022_CandyShop_Subtitle" />
				<Panel id="SectionDivider" class="ContentSpacing HorizontalCenter FullWidth">
					<Panel class="DivivderDash Left" />
					<Label class="" text="#DOTA_Talent_ComingSoonLaunchDate" />
					<Panel class="DivivderDash Right" />
				</Panel>
			</Panel>
			<Panel class="CenterContents">
				<Panel class="CandyBags">
					<Panel class="CandyBagImage" />
					<Panel class="candyBagText">
						<Label class="CandyBagCount" text="x{d:bag_count}" />
						<Label class="CandyBagTitle" text="#DOTA_International2022_CandyShop_CandyBags" />
					</Panel>
				</Panel>
				<Panel class="Description">
					<Label class="h2" text="#DOTA_International2022_CandyShop_h2" />
					<Label class="bodyText" html="true" text="#DOTA_International2022_CandyShop_Description" />
					<Panel class="ul">
						<Panel class="li">
							<Panel class="bullet" />
							<Label class="bulletText" html="true" text="#DOTA_International2022_CandyShop_Bullet1" />
						</Panel>
						<Panel class="li">
							<Panel class="bullet" />
							<Label class="bulletText" html="true" text="#DOTA_International2022_CandyShop_Bullet2" />
						</Panel>
						<Panel class="li">
							<Panel class="bullet" />
							<Label class="bulletText" html="true" text="#DOTA_International2022_CandyShop_Bullet3" />
						</Panel>
					</Panel>
				</Panel>
			</Panel>
		</Panel>
	</DOTABPInternational2022CandyShopUpcomingPage>
</root>
