<!-- xml reconstructed by ValveResourceFormat: https://vrf.steamdb.info/ -->
<root>
	<styles>
		<include src="s2r://panorama/styles/dotastyles.vcss_c" />
		<include src="s2r://panorama/styles/hudstyles.vcss_c" />
		<include src="s2r://panorama/styles/hud/hud_reborn.vcss_c" />
		<include src="s2r://panorama/styles/custom_ui.vcss_c" />
		<include src="s2r://panorama/styles/hud/dota_hud_shared_content.vcss_c" />
	</styles>
	<snippets>
		<snippet name="SharedContentItem">
			<DOTASharedContentItem class="SharedContentItem LeftRightFlow" hittest="false">
				<RadioButton id="SelectionButton" group="Announcers" class="SelectItem" />
				<Image id="SharedContentItemImage" src="s2r://panorama/images/econ/announcer/announcer_icon_default_png.vtex" class="SharedContentItemImage" />
				<Panel id="Labels" class="TopBottomFlow">
					<Label id="SharedContentItemLabel" text="#DOTA_Announcer_Default" class="SharedContentItemLabel" />
					<Label id="SharedContentCredit" text="#DOTA_HUD_SharedContentSharedBy" />
				</Panel>
			</DOTASharedContentItem>
		</snippet>
	</snippets>
	<DOTASharedContent class="TopBottomFlow" hittest="false">
		<Panel id="SharedContentHeader" hittest="false">
			<Label id="SharedContentTitle" hittest="false" text="#DOTA_SHARED_CONTENT_Title" />
			<Button id="SharedContentCloseButton" class="CloseButton" onactivate="DOTAHUDToggleSharedContent()" />
		</Panel>
		<Panel id="SharedContentContents" class="TopBottomFlow" hittest="false">
			<Panel id="SharedContentAnnouncers" class="TopBottomFlow" hittest="false">
				<Label id="AnnouncersHeader" class="SharedContentCategoryHeader" hittest="false" text="#Dota_Shared_Content_Announcer" />
				<Panel id="AnnouncersItemContainer" class="TopBottomFlow ItemsContainer" />
			</Panel>
			<Panel id="SharedContentMegaKillAnnouncers" class="TopBottomFlow" hittest="false">
				<Label id="MegaKillAnnouncersHeader" class="SharedContentCategoryHeader" hittest="false" text="#Dota_Shared_Content_Mega_Announcer" />
				<Panel id="MegaKillAnnouncersItemContainer" class="TopBottomFlow ItemsContainer" />
			</Panel>
			<Panel id="SharedContentHUDSkins" class="TopBottomFlow" hittest="false">
				<Label id="HUDSkinsHeader" class="SharedContentCategoryHeader" hittest="false" text="#Dota_Shared_Content_HUD_Skins" />
				<Panel id="HUDSkinsItemContainer" class="TopBottomFlow ItemsContainer" />
			</Panel>
		</Panel>
	</DOTASharedContent>
</root>
