<root>
	<styles>
		<include src="s2r://panorama/styles/dotastyles.vcss_c" />
		<include src="s2r://panorama/styles/tooltips/tooltip_buff.vcss_c" />
	</styles>

	<DOTATooltipBuff class="BuffContents">
		<Panel id="BuffHeader">
			<Label id="BuffName" class="TitleFont" text="#DOTA_BuffTooltip_Name" html="true" />
			<Label id="BuffLevel" text="#DOTA_BuffTooltip_Level" html="true" />
		</Panel>

		<Label id="BuffDescription" text="#DOTA_BuffTooltip_Description" html="true" />
	</DOTATooltipBuff>
</root>
