<root>
	<styles>
		<include src="s2r://panorama/styles/dotastyles.vcss_c" />
		<include src="s2r://panorama/styles/dashboard_page_shared.vcss_c" />
		<include src="s2r://panorama/styles/dashboard_page_patches.vcss_c" />
	</styles>

	<snippets>

		<snippet name="PatchNote">
			<Panel class="PatchNoteContainer">
				<Panel class="Indent" />
				<Panel class="Dot" />
				<Label class="NoteLine" text="{s:patch_note}" html="true"	/>
			</Panel>	
		</snippet>

		<snippet name="PatchSubSection">
			<Panel class="PatchSubSection">
				<Panel class="PatchSubSectionNameContainer">
					<Label class="PatchSubSectionName" text="{s:patch_sub_section_name}" />
				</Panel>
				<Panel id="PatchSubSectionContents">
					<!-- dynamic -->
				</Panel>
			</Panel>
		</snippet>
		
		<snippet name="PatchSection">
			<Panel class="PatchSection">
				<Panel class="PatchSectionNameContainer">
					<Label class="PatchSectionName" text="{s:patch_section_name}" />
				</Panel>
				<Panel id="PatchSectionContents">
					<!-- dynamic -->
				</Panel>
			</Panel>
		</snippet>

		<snippet name="ItemNotes">
			<Panel class="ItemNotes">
				<DOTAItemImage id="ItemImage" />
				<Panel class="ItemNotesContents">
					<Panel class="ItemTitle">
						<Label class="ItemName" text="{s:item_name}"/>
						<Label class="ItemTitleTag" text="- {s:item_title_tag}" html="true" />
					</Panel>
					<Panel id="ItemNotesContainer">
						<!-- dynamic -->
					</Panel>
				</Panel>
			</Panel>
		</snippet>

		<snippet name="AbilityNotes">
			<Panel class="AbilityNotes">
				<DOTAAbilityImage id="AbilityImage" />
				<Panel class="AbilityNotesContents">
					<Label class="AbilityName" text="{s:ability_name}"/>
					<Panel id="AbilityNotesContainer">
						<!-- dynamic -->
					</Panel>
				</Panel>
			</Panel>
		</snippet>

		<snippet name="HeroNotes">
			<Panel class="HeroNotes">
				<Panel class="HeroNotesTop">
					<DOTAHeroImage id="HeroImage" />
					<Panel class="HeroNotesTopContents">
						<Panel class="HeroTitle">
							<Label class="HeroName" text="{g:dota_hero_name:hero_id}"/>
							<Label class="HeroTitleTag" text="- {s:hero_title_tag}" html="true" />
						</Panel>
						<Panel id="HeroNotesContainer">
							<!-- dynamic -->
						</Panel>
					</Panel>
				</Panel>
				
				<Panel class="HeroNotesMain">
					<Panel id="AbilityNotesContainer">
						<!-- dynamic -->
					</Panel>
					
					<Panel class="TalentNotes">
						<Panel id="TalentTreeImage" />
						<Panel class="TalentNotesContents">
							<Label class="TalentsName" text="#DOTA_AbilityBuild_Talent_Title" />
							<Panel id="TalentNotesContainer">
								<!-- dynamic -->
							</Panel>
						</Panel>
					</Panel>
				</Panel>
			</Panel>
		</snippet>
		
	</snippets>

	<DOTAPatchesPage class="DashboardPage">

		<Image id="BackgroundImage" scaling="stretch-to-fit-y-preserve-aspect" />
		
		<Panel class="PatchContainer">
			<Panel id="Header">
				<Panel class="HeaderControls" >
					<Label class="GamePlayUpdate" text="#DOTA_PatchNotes_Header" />
					<DropDown id="PatchDropDown" />					
				</Panel>
			</Panel>
			<Panel id="PatchContents" AllowOversized="1">
				<!-- dynamic -->
			</Panel>		
		</Panel>

	</DOTAPatchesPage>
</root>
