<root>
	<styles>
		<include src="s2r://panorama/styles/dotastyles.vcss_c" />
		<include src="s2r://panorama/styles/dashboard_page_shared.vcss_c" />
		<include src="s2r://panorama/styles/new_bloom_shared.vcss_c" />
		<include src="s2r://panorama/styles/dashboard_page_new_bloom_2020.vcss_c" />
	</styles>

	<snippets>
		<snippet name="ConsumableAbility">
			<Panel class="ConsumableAbility">
				<Label class="ConsumableName" text="{s:ability_name}" />
				<Panel class="AbilityIconContainer">
					<Image id="AbilityImage" />
					<Label class="AbilityCharges" text="{d:charge_count}" />
				</Panel>
			</Panel>
		</snippet>
	</snippets>

	<DOTANewBloom2020Page class="DashboardPage">
		<Panel id="TempNewBloom2020Background"/>
		<DOTAScenePanel id="ModelScene" map="scenes/events/newbloom2020/parallax_newbloom2020" light="hero_light" renderdeferred="false" deferredalpha="true" particleonly="false" camera="hero_camera" rotateonmousemove="true" yawmin="0" yawmax="-1" pitchmin="-.5" pitchmax=".5" hittest="false" />
		<DOTAScenePanel id="ModelScene_fg" map="scenes/events/newblom2018/parallax_eventhome_particles" light="hero_light" renderdeferred="true" deferredalpha="true" particleonly="true" camera="hero_camera" rotateonmousemove="false" yawmin="4" yawmax="-4" pitchmin="7" pitchmax="0" hittest="false" />

		<Panel id="RewardsPanel">
			<NewBloom2020RewardList id="RewardsList" />	

			<Panel id="CourierShowcaseContainer">
				<Panel id="CourierShowcase" class="" onactivate="DOTAShowStoreItemDetailsPage( -1, 12919, 1 )" >
					<DOTAUIEconSetPreview id="CourierModel" hittest="false" hittestchildren="false" itemdef="12919" displaymode="loadout_small" drawbackground="false" renderdeferred="false" deferredalpha="true"/>
					<Panel class="InspectIcon" hittest="false"/>
					<!--                       -->
				</Panel>
				<Panel id="CourierShowcaseBase"/>
				

				<Panel id="CourierDescription">
					<Panel id="CourierIcon" />
					<Label text="#DOTA_Newbloom_EventHome_CourierReward" />
				</Panel>

			</Panel>
			
		</Panel>
		
		<Panel id="RewardsListButtons" hittest="false">
			<Button id="ScrollLeftButton" class="ArrowButton" onactivate="NewBloom2020RewardListScrollForwardLevels( RewardsList, -3 )" />
			<Button id="ScrollRightButton" class="ArrowButton" onactivate="NewBloom2020RewardListScrollForwardLevels( RewardsList, 3 )" />
		</Panel>

		<Panel id="MainContents" class="TopBottomFlow" hittest="false">
			<Panel id="TitleContainer">
				<Label id="Title" />
				<Panel id="SubtitleContainer">
					<Label id="Subtitle" text="#DOTA_NewBloom2020_Dates" />
					<Panel class="InfoIcon" onmouseover="UIShowTextTooltip( #DOTA_NewBloom2020_Dates_Tooltip )" onmouseout="UIHideTextTooltip()" />
				</Panel>
				<Label id="Description" text="#DOTA_NewBloom2020_Lore" />
			</Panel>

			<Panel id="InfoBlocks">

				<Panel id="ConsumablesInfo" class="InfoBlock">
					<Panel id="ConsumablesHeader">
						<Label text="#DOTA_NewBloom2020_ConsumablesTitle" />
						<!--                             -->
						<Panel class="InfoIcon" onmouseover="UIShowTextTooltip( #DOTA_NewBloom2020_ConsumableDescription )" onmouseout="UIHideTextTooltip()" />
					</Panel>
					<Panel id="ConsumablesList">
						<!--                                            -->
					</Panel>
					<Button id="PurchaseConsumablesButton" class="DotaPlusDarkButton" onactivate="DOTAShowStorePlusEventPage()">
						<Panel class="PurchaseButtonContent">
							<Panel class="DotaPlusCurrencyIcon" />
							<Label text="#DOTA_NewBloom2020_ConsumablePurchase" />
						</Panel>
					</Button>
				</Panel>
	
				<Panel id="RewardsInfo" class="InfoBlock">
					
					<Panel id="Rewards">
						<Panel id="RewardsHeader">
							<Label id="RewardsTitle" text="#DOTA_NewBloom2020_RewardsTitle" />
							<!--                             -->
							<Panel class="InfoIcon" onmouseover="UIShowTextTooltip( #DOTA_NewBloom2020_RewardsDescription )" onmouseout="UIHideTextTooltip()" />
						</Panel>
						<Label id="RewardsDescription" text="#DOTA_NewBloom2020_RewardsDescription" />

						<Panel id="CurrentLevelContainer">
							<Panel id="EventLevel">
								<Panel id="EventLevelBadge"/>
								<Label id="EventLevelNumber" text="{d:current_level}"/>
							</Panel>
							<Panel id="PurchaseAndLevels" class="TopBottomFlow">
								<Panel id="CurrentLevelInfo">

									<Label id="DailyBonusAvailable" text="#DOTA_NewBloom2020_DailyBonusAvailable" />
									<Panel id="DailyBonusUsed" >
										<Label text="#DOTA_NewBloom2020_DailyBonusClaimed" />
										<Countdown id="DailyBonusCountdown">
											<Label text="#DOTA_NewBloom2020_NextDailyBonus" />
										</Countdown>
									</Panel>
									<ProgressBar id="CurrentLevelProgress" />
									<Label class="EventLevelProgressText" text="#DOTA_EventLevelPointsProgress" />
								</Panel>
								<Panel id="EventEndInfo" class="TopBottomFlow">
									<Label id="LabelEventEnded" text="#DOTA_NewBloom2020_Concluded" />
									<Label id="LabelUseConsumables" text="#DOTA_NewBloom2020_Dates_Expire" html="true"/>
								</Panel>
							</Panel>
						</Panel>
					</Panel>

				</Panel>

			</Panel>	

		</Panel>
	
	</DOTANewBloom2020Page>
</root>
