<root>
	<styles>
		<include src="s2r://panorama/styles/dotastyles.vcss_c" />
		<include src="s2r://panorama/styles/dashboard_page_shared.vcss_c" />
		<include src="s2r://panorama/styles/dashboard_page_ticket_code.vcss_c" />
	</styles>

	<DOTATicketCodePage class="DashboardPage SafeDashboardPage">

    <Panel class="LeftRightFlow">
      <Label class="TicketCodeLabel" text="Damai Access Code:" />
      <Label class="TicketCodeValue" text="{s:damai_code}" />
    </Panel>

  </DOTATicketCodePage>

</root>
