<root>
	<styles>
		<include src="s2r://panorama/styles/dotastyles.vcss_c" />
		<include src="s2r://panorama/styles/post_game_progress.vcss_c" />
	</styles>

	<scripts>
		<include src="s2r://panorama/scripts/util.vjs_c" />
		<include src="s2r://panorama/scripts/sequence_actions.vjs_c" />
		<include src="s2r://panorama/scripts/mvp_accolade_type_map.vjs_c" />
		<include src="s2r://panorama/scripts/post_game_mvp.vjs_c" />
		<include src="s2r://panorama/scripts/post_game_progress/post_game_progress_utils.vjs_c" />
		<include src="s2r://panorama/scripts/post_game_progress/post_game_progress_screens.vjs_c" />
		<include src="s2r://panorama/scripts/post_game_progress/post_game_progress_coach_rating.vjs_c" />
		<include src="s2r://panorama/scripts/post_game_progress/post_game_progress_hero_badge.vjs_c" />
		<include src="s2r://panorama/scripts/post_game_progress/post_game_progress_hero_relics.vjs_c" />
		<include src="s2r://panorama/scripts/post_game_progress/post_game_progress_match_rewards.vjs_c" />
		<include src="s2r://panorama/scripts/post_game_progress/post_game_progress_sequence.vjs_c" />
	</scripts>

	<snippets>

		<!-- MVP 2.0 -->
		<snippet name="HonorableMention">
			<Panel class="HonorableMention">
				<Panel class="HeroCenterContent" hittest="false">
					<Panel id="HeroBackground" hittest="false">
						<Panel class="HeroBackgroundImage"/>
						<Panel class="HeroSelectGlow"/>
						<Panel class="Accolades" id="Accolades"/>
						<DOTAScenePanel id="HonorableMentionModel" class="OverviewHeroRender" unit="npc_dota_hero_rubick" drawbackground="0"  antialias="true" activity-modifier="PostGameIdle" particleonly="false" />
						<Panel class="HeroImageOverlay" hittest="false"/>
					</Panel>
					<Label id="PlayerName"	class="OverviewHeroPlayerName" hittest="false" html="true" text="{g:dota_persona:ng:user_account_id}"/>
					<Label id="BotPlayerName" class="OverviewHeroPlayerName" hittest="false" text="{s:bot_player_name}"/>
					<Label class="Guildname" hittest="false" html="true" text="{g:dota_guild_name:user_guild_id}"/>
					<DOTAHeroImage id="MainHeroImage" heroimagestyle="landscape" scaling="stretch-to-fit-preserve-aspect" />
				</Panel>
			</Panel>
		</snippet>

		<snippet name="MVPAccolade">
			<Panel class="Accolade MVPAccolade">
				<Panel class="gradient" id="gradient"/>
				<Panel class="icon" id="icon"/>
				<DOTAAbilityImage class="ability_icon" id="ability_icon"/>
				<Label class="title" text="{s:title}"/>
				<Label class="details" id="details" text="{s:details}" html="true"/>
			</Panel>
		</snippet>

		<!-- MVP Voting Progress -->

		<snippet name="MVPVotingProgress">
			<Panel class="ProgressScreen" >
				<DOTAPostGameMVPVote id="PostGameMVPVote" />
			</Panel>
		</snippet>

		<!-- Gauntlet Mode Progress -->
		<snippet name="GauntletProgress">
			<Panel class="ProgressScreen" onactivate="StartSkippingAhead()">
				<Panel class="BattlePassBackground">
					<Panel class="BattlePassShieldImage" />
					<Panel class="BattlePassBackgroundImage" />
				</Panel>

				<Panel class="GauntletProgressMain">
					
					<Label class="GauntletProgressTitle" text="#DOTA_Gauntlet_PlayLabel" />
					
					<Panel id="GauntletTier">
								<Label class="GauntletLabel" text="#DOTA_Gauntlet_GauntletTierTopLabel" />
								<Label class="GauntletBigLabel GauntletTier" text="#DOTA_Gauntlet_GauntletTierLabel" />
					</Panel>
					<Panel id="GauntletHeroArt">
						<!-- <Panel id="GauntletHeroesLeft" />
						<Panel id="GauntletHeroesRight" /> -->
					</Panel>
					
					<Panel class="GauntletProgressSpacer" />
					<Panel class="GauntletPipContainer">
						<Panel id="GauntletWin0" class="GauntletPip GauntletWin" />
						<Panel id="GauntletWin1" class="GauntletPip GauntletWin" />
						<Panel id="GauntletWin2" class="GauntletPip GauntletWin" />
						<Panel class="GauntletPipSpacer" />
						<Panel id="GauntletLose0" class="GauntletPip GauntletLose" />
						<Panel id="GauntletLose1" class="GauntletPip GauntletLose" />
					</Panel>
					<Panel class="GauntletComplete">
						<Panel class="GauntletInfo GauntletInfo__Win">
							<Label class="GauntletInfoDesc" text="#DOTA_GauntletPostGame_Win" />
						</Panel>
						<Panel class="GauntletInfo GauntletInfo__Promote">
							<Label class="GauntletInfoDesc" text="#DOTA_GauntletPostGame_Promote" />
						</Panel>
						<Panel class="GauntletInfo GauntletInfo__Lose">
							<Label class="GauntletInfoDesc" text="#DOTA_GauntletPostGame_Lose" />
						</Panel>
						<Panel class="GauntletInfo GauntletInfo__InProgress">
							<Label class="GauntletInfoDesc" text="#DOTA_GauntletPostGame_InProgress" />
						</Panel>
						<Panel class="GauntletInfo GauntletInfo__Rewards">
							<Panel class="GauntletInfoRewards GauntletInfoRewards__SideShop">
								<Label class="GauntletRewardsLabel" text="+{d:gauntlet_gold}"/>
								<Panel class="GauntletRewardsIcon" />
							</Panel>
							<Panel class="GauntletInfoRewards GauntletInfoRewards__PlusShards">
								<Label class="GauntletRewardsLabel" text="+{d:gauntlet_shards}" />
								<Panel class="GauntletRewardsIcon DotaPlusCurrencyIcon" />
							</Panel>
						</Panel>
					</Panel>
				</Panel>

				<Panel class="GauntletBattlePassProgress">
					<Panel id="BattlePassProgressCenter">
						<Panel class="BattlePassProgressBarTop">
							<DOTAEventLevelShield id="BattlePassLevelShield" />
							<Panel class="BattlePassPointsTotalContainer">
								<!-- <Label class="BattlePassPointsTotalTitle" text="#DOTA_BattlePassPostGame_Total" /> -->
								<Panel class="BattlePassPointsTotalGlowContainer">
									<Label class="BattlePassPointsTotal" text="+{d:total_points_gained}" />
								</Panel>
							</Panel>
						</Panel>

						<Panel id="BattleLevelProgressContainer">
							<!-- <Panel class="BattleShieldSpacer" /> -->
							<Panel class="ProgressBarContainer" >
								<ProgressBarWithMiddle id="BattleLevelProgress" min="0" max="1000" />
								<Panel id="BattleLevelProgressSection">
									<Label class="BattlePassProgressLevelProgressTitle" text="#DOTA_BattlePassPostGame_LevelProgress" />
									<Label class="BattlePassLevelProgressBP" text="#DOTA_BattlePass_BPProgress" />
								</Panel>
							</Panel>
						</Panel>
					</Panel>
				</Panel>

				<!-- should be last to stay on top -->
				<Panel id="GauntletAnimatePip" class="GauntletAnimatePip" />
			</Panel>
		</snippet>
		
		<!-- Hero Badge Progress Screen -->

		<snippet name="HeroBadgeProgress">
			<Panel class="ProgressScreen" onactivate="StartSkippingAhead()">

				<Panel class="PlusBackground" />

				<Panel id="HeroBadgeProgressMain">
					<DOTAScenePanel id="HeroBadgeHeroModel" particleonly="false" antialias="true" />

					<Panel id="HeroBadgeProgressCenter">
						<Panel class="HeroProgressTitle">
							<Panel class="HeroProgressPlusIcon" />
							<Label text="#DOTA_PlusPostGame_HeroProgress" />
						</Panel>

						<Panel id="HeroBadgeLevelProgressSection">
							<Label class="HeroBadgeProgressLevelProgressTitle" text="#DOTA_PlusPostGame_LevelProgress" />
							<Label class="HeroBadgeLevelProgressXP" text="#DOTA_Plus_XPProgress" />
						</Panel>

						<Panel id="HeroBadgeLevelProgressContainer">
							<ProgressBar id="HeroBadgeLevelProgress" min="0" max="1000" />
						</Panel>

						<Label class="HeroBadgeProgressCurrentLevel" text="#DOTA_PlusPostGame_CurrentLevel" />

						<Panel id="HeroBadgeProgressCore">
							<Panel id="HeroBadgeProgressXPGrid">
								<Panel id="HeroBadgeProgressRows">

								</Panel>
								<Panel id="TotalsRow" class="HeroBadgeProgressRow">
									<Label class="HeroBadgeProgressRowType" text="#DOTA_PlusPostGame_Total" />
									<Label class="HeroBadgeProgressRowValue" text="#DOTA_PlusPostGame_XPValue" />
								</Panel>
							</Panel>
						</Panel>
					</Panel>

					<Panel id="HeroRelicsProgressCenter">
						<Panel class="HeroProgressTitle">
							<Panel class="HeroProgressPlusIcon" />
							<Label text="#DOTA_PlusPostGame_RelicsProgress" />
						</Panel>
						<Panel id="HeroRelicsProgressList">
						</Panel>
					</Panel>

					<DOTAHeroBadge id="HeroBadgeProgressHeroBadge" badgestyle="icon" />
				</Panel>
				<Panel id="HeroBadgeLevelUpPanel" >
					<DOTAScenePanel id="LevelUpRankScene" map="scenes/hero_level_icon" camera="shot_camera" renderdeferred="true" deferredalpha="true" antialias="true" hittest="false" particleonly="false" />
					<Label id="LevelUpTitle" text="#DOTA_PlusPostGame_LevelUp" />
					<Label id="LevelUpValue" text="#DOTA_PlusPostGame_CurrentLevel" />

					<Panel id="HeroBadgeProgressRewards">
						<Panel id="HeroBadgeProgressRewardsList" />
						<TextButton id="RewardsFinishedButton" class="PopupButton" text="#DOTA_Continue" />
					</Panel>
				</Panel>
			</Panel>
		</snippet>

		<snippet name="HeroBadgeProgressRow">
			<Panel class="HeroBadgeProgressRow">
				<Label class="HeroBadgeProgressRowType" text="{s:xp_type}" />
				<Label class="HeroBadgeProgressRowValue" text="#DOTA_PlusPostGame_XPValue" />
			</Panel>
		</snippet>

		<snippet name="HeroBadgeProgressRow_Challenge">
			<Panel class="HeroBadgeProgressRow HeroBadgeProgressRow_Challenge">
				<Panel class="HeroBadgeProgressRowChallengeDetails">
					<Label class="HeroBadgeProgressRowType" text="{s:xp_type}" />
					<Panel class="HeroBadgeProgressRowChallengeDetailsBottom">
						<Panel class="HeroBadgeProgressRowChallengeStars">
							<Panel class="HeroBadgeProgressRowChallengeStar Star1" />
							<Panel class="HeroBadgeProgressRowChallengeStar Star2" />
							<Panel class="HeroBadgeProgressRowChallengeStar Star3" />
						</Panel>
						<Label class="HeroBadgeProgressRowChallengeName" text="{s:challenge_name}" html="true" />
					</Panel>
				</Panel>
				<Label class="HeroBadgeProgressRowValue" text="#DOTA_PlusPostGame_XPValue" />
			</Panel>
		</snippet>

		<snippet name="HeroBadgeProgressRow_ShardReward">
			<Panel class="HeroBadgeProgressRow ShardReward">
				<Label class="HeroBadgeProgressRowType" text="{s:reward_type}" />
				<Label class="HeroBadgeProgressRowValue" text="#DOTA_PlusPostGame_ShardValue" />
				<Panel class="DotaPlusCurrencyIcon" />
			</Panel>
		</snippet>

		<snippet name="HeroBadgeLevelUpRewardTier">
			<Panel class="HeroBadgeLevelUpRewardTier HeroBadgeLevelUpReward">
				<Panel class="HeroBadgeLevelUpRewardImage PlusHeroBadgeIcon" />
				<Label class="HeroBadgeLevelUpRewardValue" text="#DOTA_PlusRewards_TierName" />
				<Panel class="HeroBadgeLevelUpRewardLine" />
				<Label class="HeroBadgeLevelUpRewardTitle" text="#DOTA_PlusRewards_HeroBadge" />
			</Panel>
		</snippet>

		<snippet name="HeroBadgeLevelUpRewardChatWheel">
			<Panel class="HeroBadgeLevelUpRewardChatWheel HeroBadgeLevelUpReward">
				<Panel id="Icon" class="HeroBadgeLevelUpRewardImage DotaPlusChatWheelIcon" acceptsfocus="true" />
				<Label class="HeroBadgeLevelUpRewardValue" text="&quot;{s:all_chat_prefix}{s:chat_wheel_message}&quot;" />
				<Panel class="HeroBadgeLevelUpRewardLine" />
				<Label class="HeroBadgeLevelUpRewardTitle" text="#DOTA_PlusRewards_HeroChatWheel" />
			</Panel>
		</snippet>

		<snippet name="HeroBadgeLevelUpRewardCurrency">
			<Panel class="HeroBadgeLevelUpRewardCurrency HeroBadgeLevelUpReward">
				<Panel class="HeroBadgeLevelUpRewardImage DotaPlusCurrencyIcon" />
				<Label class="HeroBadgeLevelUpRewardValue" text="{d:currency_amount}" />
				<Panel class="HeroBadgeLevelUpRewardLine" />
				<Label class="HeroBadgeLevelUpRewardTitle" text="#DOTA_Plus_Currency" />
			</Panel>
		</snippet>
		
		<snippet name="HeroRelicsProgress">
			<Panel class="ProgressScreen" onactivate="StartSkippingAhead()">

				<Panel class="PlusBackground" />

				<Panel id="HeroRelicsProgressMain">
					<DOTAScenePanel id="HeroRelicsHeroModel" particleonly="false" antialias="true" />

					<Panel id="HeroRelicsProgressCenter">
						<Panel class="HeroProgressTitle">
							<Panel class="HeroProgressPlusIcon" />
							<Label text="#DOTA_PlusPostGame_RelicsProgress" />
						</Panel>
						<Panel id="HeroRelicsProgressList">
						</Panel>
					</Panel>
				</Panel>
			</Panel>
		</snippet>
		
		<snippet name="SingleRelicProgress">
			<Panel class="SingleRelicProgress">
				<Panel class="SingleRelicImageContainer">
					<DOTAHeroRelicImage id="SingleRelicImage" />
				</Panel>
				<Panel class="SingleRelicProgressDetails">
					<Panel class="SingleRelicProgressValues">
						<Label class="SingleRelicCurrentProgress" text="{d:current_progress}" />
						<Label class="SingleRelicIncrementAmount" text="+{d:increment}" />
						<Label id="SingleRelicLevelUpLabel" text="#DOTA_BattlePassPostGame_LevelUp" />
					</Panel>
					<ProgressBar id="SingleRelicProgressBar" min="0" />
					<Label class="SingleRelicName" text="{g:dota_gem_name:relic_type}" />
					<Panel class="RelicLevelContainer">
						<Label class="HeroRelicLevelLabel" text="#DOTA_HeroRelics_Level" />
						<Label class="SingleRelicLevel" text="{s:relic_level}" />
					</Panel>
				</Panel>
			</Panel>
		</snippet>
		
		<snippet name="MatchRewardsProgress">
			<Panel class="ProgressScreen" onactivate="StartSkippingAhead()">
				<Label class="MatchRewardsTitle" text="#DOTA_MatchRewards" />
				<Panel class="MatchRewardsSections">
					<Panel id="HeroLevelMatchRewardsSection" class="MatchRewardsSection">
						<Panel class="MatchRewardsSectionBackground" />
						<DOTAScenePanel id="MatchRewardsHeroLevelModel" particleonly="false" antialias="true" drawbackground="false" />
						<Panel class="MatchRewardsSectionMain">
							<Label class="MatchRewardsSectionTitle" text="{g:dota_hero_name:hero_id}" />
							<Panel class="MatchRewardsSectionControls">
								<Panel class="MatchRewardsHeroLevelProgressContainer">
									<ProgressBar id="MatchRewardsHeroLevelProgressBar" />
									<Label class="MatchRewardsHeroLevelProgressLabel" text="#DOTA_Plus_XPProgress" />
								</Panel>
								<DOTAHeroBadge id="MatchRewardsHeroBadge" />
							</Panel>
							<Panel class="MatchRewardsHeroXPTableContainer">
								<Panel class="MatchRewardsDivider" />
								<Panel id="MatchRewardsHeroXPTable" class="MatchRewardsTable">
									<!-- dynamic -->
								</Panel>
							
								<Panel class="MatchRewardsDivider" />
								<Panel id="MatchRewardsTableTotalsRow" class="MatchRewardsTableRow ShowRow ShowValue">
									<Label class="MatchRewardsTableRowLabel" text="#DOTA_MatchRewards_TotalHeroXP" />
									<Label class="MatchRewardsTableRowValue" text="#DOTA_PlusPostGame_XPValue" />
								</Panel>
							</Panel>
							<Panel class="MatchRewardsHeroLevelPlusRestrictedContainer DotaPlusContainer">
								<Panel class="MatchRewardsHeroLevelPlusRestrictedCenter">
									<Label text="#DOTA_PlusPostGame_LevelRestricted" />
									<Panel class="MatchRewardsHeroLevelPlusRestrictedImage" />
								</Panel>
							</Panel>
						</Panel>
						<Panel id="HeroBadgeLevelUpPanel" >
							<DOTAScenePanel id="LevelUpRankScene" map="scenes/hero_level_icon" camera="shot_camera" renderdeferred="true" deferredalpha="true" antialias="true" hittest="false" particleonly="false" />
							<Label id="LevelUpTitle" text="#DOTA_PlusPostGame_LevelUp" />
							<Label id="LevelUpValue" text="#DOTA_PlusPostGame_CurrentLevel" />

							<Panel id="HeroBadgeProgressRewards">
								<Panel id="HeroBadgeProgressRewardsList" />
								<TextButton id="RewardsFinishedButton" class="PopupButton" text="#DOTA_Continue" />
							</Panel>
						</Panel>

					</Panel>
					<Panel id="ShardsMatchRewardsSection" class="MatchRewardsSection">
						<Panel class="MatchRewardsSectionBackground" />
						<Panel class="MatchRewardsShardsHeader" />
						<Panel class="MatchRewardsSectionMain">
							<Label class="MatchRewardsSectionTitle" text="{d:current_shards}" />
							<Panel class="MatchRewardsSectionControls">
								<Label class="MatchRewardsShardsTitle" text="#DOTA_MatchRewards_YourShards" />
							</Panel>
							<Panel class="MatchRewardsDivider" />
							<Panel id="MatchRewardsShardsTable" class="MatchRewardsTable">
								<!-- dynamic -->
							</Panel>
							<Panel class="MatchRewardsDivider" />
							<Panel id="MatchRewardsTableTotalsRow" class="MatchRewardsTableRow ShowRow ShowValue">
								<Label class="MatchRewardsTableRowLabel" text="#DOTA_MatchRewards_TotalShards" />
								<Label class="MatchRewardsTableRowValue" text="+{d:shard_value}" />
								<Panel class="DotaPlusCurrencyIcon" />
							</Panel>
						</Panel>
					</Panel>
					<Panel id="GuildMatchRewardsSection" class="MatchRewardsSection">
						<Panel class="MatchRewardsSectionBackground" />
						<DOTAGuildImage id="MatchRewardsGuildImage" />
						<Panel class="MatchRewardsSectionMain">
							<Label class="MatchRewardsSectionTitle" text="{g:dota_guild_name:guild_id}" />
							<Panel class="MatchRewardsSectionControls" />
							<Panel class="MatchRewardsDivider TopDivider" />
							<Panel class="MatchRewardsGuildItems">
								
								<Panel id="MatchRewardsGuildContracts">
									<!-- dynamic -->
								</Panel>
								<Panel class="MatchRewardsGuildChallenge">
									<Label class="MatchRewardsGuildChallengeLabel" text="#DOTA_MatchRewards_GuildChallenge" />
									<Panel class="MatchRewardsGuildChallengeCenter">
										<Image id="MatchRewardsGuildChallengeImage" scaling="stretch-to-fit-preserve-aspect" />
										<Label class="MatchRewardsGuildChallengeDescription" text="{s:challenge_description}" html="true" />
									</Panel>
									<Panel class="MatchRewardsGuildChallengeProgressBarContainer">
										<ProgressBarWithMiddle id="MatchRewardsGuildChallengeProgressBar" />
										<Label text="{d:challenge_start_value}/{d:challenge_max_value} &lt;span class=&quot;ChallengeProgress&quot;&gt;+{d:challenge_progress}&lt;/span&gt;" html="true"/>
									</Panel>
								</Panel>
								
							</Panel>
							
							<Panel id="MatchRewardsGuildPointsTable" class="MatchRewardsTable">
								<!-- dynamic -->
							</Panel>
							
							<Panel class="MatchRewardsDivider" />

							<Panel id="MatchRewardsTableTotalsRow" class="MatchRewardsTableRow ShowRow ShowValue">
								<Label class="MatchRewardsTableRowLabel" text="#DOTA_MatchRewards_TotalGuildPoints" />
								<Label class="MatchRewardsTableRowValue" text="#DOTA_GuildPointsIncrease" />
							</Panel>	
						</Panel>
					</Panel>
				</Panel>
				<Panel id="MatchRewardsSmoke" hittest="false" />
			</Panel>
			
		</snippet>

		<snippet name="MatchRewardsHeroXPRow">
			<Panel class="MatchRewardsTableRow">
				<Label class="MatchRewardsTableRowLabel" text="{s:xp_type}" />
				<Label class="MatchRewardsTableRowValue" text="#DOTA_PlusPostGame_XPValue" />
			</Panel>
		</snippet>

		<snippet name="MatchRewardsHeroXPRow_Challenge">
			<Panel class="MatchRewardsTableRow MatchRewardsHeroXPRow_Challenge">
				<Panel class="MatchRewardsChallengeDetails">
					<Label class="MatchRewardsTableRowLabel" text="{s:xp_type}" />
					<Panel class="MatchRewardsChallengeDetailsBottom">
						<Panel class="MatchRewardsChallengeStars">
							<Panel class="MatchRewardsChallengeStar Star1" />
							<Panel class="MatchRewardsChallengeStar Star2" />
							<Panel class="MatchRewardsChallengeStar Star3" />
						</Panel>
						<Label class="HeroBadgeProgressRowChallengeNameTurboOnly" text="{s:challenge_name}" html="true" 
						    onmouseover="UIShowTextTooltip(#DOTA_HeroBadgeProgressTurboLimitedGains)"
							onmouseout="UIHideTextTooltip()"
						   />
						<Label class="HeroBadgeProgressRowChallengeName" text="{s:challenge_name}" html="true"/>
					</Panel>
				</Panel>
				<Label class="MatchRewardsTableRowValue" text="#DOTA_PlusPostGame_XPValue" />
			</Panel>
		</snippet>
		
		<snippet name="MatchRewardsShardRow">
			<Panel class="MatchRewardsTableRow">
				<Label class="MatchRewardsTableRowLabel" text="{s:reward_type}" />
				<Label class="MatchRewardsTableRowValue" text="#DOTA_PlusPostGame_ShardValue" />
				<Panel class="DotaPlusCurrencyIcon" />
			</Panel>
		</snippet>
		
		<snippet name="MatchRewardsGuildContract">
			<Panel class="MatchRewardsGuildContract">
				<DOTAGuildContract id="GuildContract" />
				<Panel class="ContractCompletedIcon" />
			</Panel>
		</snippet>
		
		<snippet name="MatchRewardsGuildPointsRow">
			<Panel class="MatchRewardsTableRow">
				<Label class="MatchRewardsTableRowLabel" text="{s:reward_type}" />
				<Label class="MatchRewardsTableRowValue" text="#DOTA_GuildPointsIncrease" />
			</Panel>
		</snippet>

		<snippet name="BattlePassTip">
			<Panel class="BattlePassTip">
				<DOTAAvatarImage id="Avatar" />
				<Panel class="TipCountContainer">
					<Panel class="TipToken First" />
					<Panel class="TipToken Second" />
					<Panel class="TipToken Third" />
				</Panel>
			</Panel>
		</snippet>
		
		<snippet name="BattlePassAction">
			<Panel class="BattlePassAction">
				<Image id="ConsumableImage" />	
				<Panel class="ActionDescription">
					<Label class="ActionCount" text="{d:action_quantity}x" />
					<Label class="ActionPoints" text="{d:action_points}" />	
				</Panel>
			</Panel>
		</snippet>
		
		<snippet name="BattlePassXPCircle">
			<Panel class="BattlePassXPCircle">
				<Panel class="XPCircle">
					<Label id="PTS"/>
					<Label class="PointsLabel" text="{d:xp_circle_points}"/>
				</Panel>
			</Panel>
		</snippet>

		<snippet name="BattlePassGuildContract">
			<Panel class="BattlePassGuildContract">
				<DOTAGuildContract id="GuildContract" />
				<Panel class="ContractCompletedIcon" />
			</Panel>
		</snippet>

		<!-- Spring 2021 Progress Screen -->
		<snippet name="Spring2021WeeklyProgressEntry">
			<Panel class="WeeklyProgressBarContainer">
				<ProgressBarWithMiddle id="ProgressBar" class="ProgressBarLarge"/>
				<Panel class="WeeklyNameValueContainer">
					<Label class="WeeklyProgressItemName" text="{s:progress_name}"/>
					<Label class="WeeklyProgressItemValue" text="{d:progress_start_value}/{d:progress_max_value} &lt;span class=&quot;Spring2021Progress&quot;&gt;+{s:progress}&lt;/span&gt;" html="true"/>
				</Panel>	
				<Label class="AchievementDescription" text="{s:progress_description}" html="true" />					
			</Panel>
		</snippet>
	
		<snippet name="Spring2021Progress" >
			<Panel class="ProgressScreen" onactivate="StartSkippingAhead()" >

				<Panel class="Spring2021Background">
					<Panel class="Spring2021ShieldImage" />
					<Panel class="Spring2021BackgroundImage" />
				</Panel>

				<Panel id="Spring2021ProgressMain" hittest="false">

					<Panel class="Spring2021ProgressTitle">
						<Panel class="Spring2021ProgressTitleGlowContainer">
							<Label class="Spring2021ProgressTitleText" text="#DOTA_Spring2021PostGame_Progress" />
						</Panel>
						<Panel class="NemesticeLogo" >	
							<DOTAScenePanel class="NemesticeLogoFX" camera="shot_cameraA" map="scenes/events/nemestice/nemestice_logo_fx" particleonly="true"/>
						</Panel>

					</Panel>

					<Panel id="Spring2021ProgressCore">
						<Panel id="Spring2021WeeklyProgress" class="Spring2021ProgressTypeContainerLarge">
							<Panel class="Spring2021WeeklyProgressTitleContainer">
								<Panel class="WeeklyProgressLogo" />
								<Label class="ProgressTypeTitle" text="#DOTA_WeeklyQuests" />
							</Panel>
							<Panel class="Spring2021ProgressTypeDetails" id="Spring2021WeeklyProgressTypeDetails">
								<!-- filled by js -->
							</Panel>
						</Panel>
						
						<Panel id="Spring2021EventGameNemesticeProgress" class="Spring2021ProgressTypeContainer">
							<Label class="ProgressTypeTitle" text="#DOTA_BattlePassPostGame_EventGameProgress_2021" />
							<Panel class="Spring2021ProgressTypeDetails">
								<Panel class="EventGame_Progress">
									<Label text="#DOTA_BattlePassPostGame_EventGameNemestice_WeeklyCap" class="EventGame_Progress_Cap" />
									<ProgressBarWithMiddle id="EventGameWeeklyProgress" class="EventGame_Progress_Bar" />
									<Label text="#DOTA_BattlePassPostGame_EventGameNemestice_WeeklyProgress" class="WeeklyChallengeProgressLabel" html="true"/>
								</Panel>

							</Panel>
							<Panel id="XPCircleContainer" />
						</Panel>
						<Panel id="Spring2021CavernCrawlProgress" class="Spring2021ProgressTypeContainer">
							<Panel class="CavernCrawlTitleContainer">
								<Panel class="CavernCrawlLogo" />
								<Label class="ProgressTypeTitle" text="#DOTA_Spring2021PostGame_CavernCrawlProgress" />
							</Panel>
							<Panel class="Spring2021ProgressTypeDetails">
								<Panel class="CavernCrawlMap">
									<Panel class="MapImage" />
									<DOTAHeroMovie id="CavernCrawlHero" class="Spring2021ProgressHeroMovie" scaling="none" />
								</Panel>
								<Panel class="ProgressCompletedContainer">
									<Label class="ProgressCompleted" text="#DOTA_Spring2021PostGame_Complete" />
								</Panel>
							</Panel>
							<Panel id="StarContainer" >
								<Panel class="Star Filled"/>
							</Panel>
						</Panel>
					</Panel>

					<Panel id="Spring2021ProgressCenter" class="LeftRightFlow">

						<Panel class="BattlePassWeeklyProgress">
							<Label class="SeasonAchievementsProgress" text="#DOTASpring2021EventSummaryWeekActive" />
								<Panel class="SeasonStatus">
									<Panel class="LeftRightFlow">
										<Panel class="PointTotalIcon"/>
										<Label class="SeasonAchievementsRewards" text="#DOTA_Spring2021_WeeklyQuest_PointsAvailable" html="true" />
									</Panel>
								</Panel>
								<DOTAWeeklyQuestPipBar id="WeeklyQuestProgressPipBar"/>
							
						</Panel>
						
						<Panel id="BattlePassProgressCenter">
							<Panel class="BattlePassProgressBarTop">
								<DOTAEventLevelShield id="BattlePassLevelShield" />
								<Panel class="BattlePassPointsTotalContainer">
									<Label class="BattlePassPointsTotalTitle" text="#DOTA_BattlePassPostGame_TotalEarned" />
									<Panel class="BattlePassPointsTotalGlowContainer">
										<Label class="BattlePassPointsTotal" text="+{d:total_points_gained}" />
									</Panel>
								</Panel>
								<Panel id="BattleLevelProgressContainer">
									<Panel class="ProgressBarContainer" >
										<Label class="BattlePassProgressLevelProgressTitle" text="#DOTA_BattlePassPostGame_LevelProgress" />
										<ProgressBarWithMiddle id="BattleLevelProgress" min="0" max="1000" />
										<Panel id="BattleLevelProgressSection">
											<Label class="BattlePassLevelProgressBP" text="#DOTA_BattlePass_BPProgress" />
										</Panel>
									</Panel>
								</Panel>
							</Panel>
						</Panel>
						
					</Panel>
				</Panel>
				
			</Panel>
		</snippet>

		<!-- BattlePoints Progress Screen -->
		<snippet name="BattlePassProgress" >
			<Panel class="ProgressScreen" onactivate="StartSkippingAhead()" >

				<Panel class="BattlePassBackground">
					<Panel class="BattlePassShieldImage" />
					<Panel class="BattlePassBackgroundImage" />
				</Panel>

				<Panel id="BattlePassProgressMain" hittest="false">

					<Panel class="BattlePassProgressTitle">
						<!-- <Panel class="BattlePassLogo" /> -->
						<Panel class="BattlePassProgressTitleGlowContainer">
							<Label class="BattlePassProgressTitleText" text="#DOTA_BattlePassPostGame_Progress" />
							<!-- <Label class="BattlePassProgressTitleText" text="#DOTA_BattlePassPostGame_Progress" /> -->
						</Panel>
					</Panel>
					
					<Panel id="BattlePassProgressCore">

						<Panel id="BattlePassEventGameTI9Progress" class="BattlePassProgressTypeContainer">
							<Label class="ProgressTypeTitle" text="#DOTA_BattlePassPostGame_EventGameProgress_2019" />
							<Panel class="BattlePassProgressTypeDetails">
								<Panel class="EventGame_Margin">
									<Panel class="EventGame_Win">
										<Label class="EventGame_Label_Title" text="#DOTA_BattlePassPostGame_EventGame_Win" />
										<Label class="EventGame_Label_Progress" text="#DOTA_BattlePassPostGame_EventGame_WinPoints" />
									</Panel>
									<Panel class="EventGame_WinBonus">
										<Label class="EventGame_Label_Title" text="#DOTA_BattlePassPostGame_EventGame_WinBonus" />
										<Label class="EventGame_Label_Progress" text="#DOTA_BattlePassPostGame_EventGame_WinBonusPoints" />
									</Panel>
									<Panel class="EventGame_Loss">
										<Label class="EventGame_Label_Title" text="#DOTA_BattlePassPostGame_EventGame_Loss" />
										<Label class="EventGame_Label_Progress" text="#DOTA_BattlePassPostGame_EventGame_LossPoints" />
									</Panel>
									<Panel class="EventGame_Treasure">
										<Label class="EventGame_Label_Title" text="#DOTA_BattlePassPostGame_EventGame_Treasure" />
										<Label class="EventGame_Label_Progress" text="#DOTA_BattlePassPostGame_EventGame_TreasurePoints" />
									</Panel>
								</Panel>
								<Panel class="EventGame_Progress">
									<Label text="#DOTA_BattlePassPostGame_EventGame_WeeklyCap" class="EventGame_Progress_Cap" />
									<ProgressBarWithMiddle id="EventGameWeeklyProgress" class="EventGame_Progress_Bar" />
									<Label text="#DOTA_BattlePassPostGame_EventGame_WeeklyProgress" class="WeeklyChallengeProgressLabel" />
								</Panel>
							</Panel>
							<Panel id="XPCircleContainer" />
						</Panel>

						<Panel id="BattlePassEventGameTI10Progress" class="BattlePassProgressTypeContainer">
							<Label class="ProgressTypeTitle" text="#DOTA_BattlePassPostGame_EventGameProgress_2020" />
							<Panel class="BattlePassProgressTypeDetails">
								<Panel class="EventGame_Margin">
									<Label text="#DOTA_BattlePassPostGame_EventGameTI10_ArcaneFragments" class="EventGame_PremiumProgress_Cap" />							
									<Label text="#DOTA_BattlePassPostGame_EventGameTI10_ArcaneFragments_Desc" class="EventGame_PremiumProgress_Cap Subtitle" />							
									<Panel class="PremiumCircle">
										<Label id="PremiumPTS"/>
										<Label class="PremiumPointsLabel" text="+{d:premium_points}"/>
										<Panel>
											<Label class="PremiumPointsLabel Multiplier Glow" text="x 3" />
											<Label class="PremiumPointsLabel Multiplier" text="x 3" />
										</Panel>
									</Panel>			
									<Label class="ExtraPremiumPointsLabel" text="+{d:extra_premium_points}"/>
								</Panel>
								<Panel class="EventGame_PremiumProgress">
									<Label html="true" text="#DOTA_BattlePassPostGame_EventGameTI10_WeeklyPremiumCap" class="EventGame_PremiumProgress_Cap" />
									<ProgressBarWithMiddle id="EventGameWeeklyPremiumProgress" class="EventGame_PremiumProgress_Bar" />
									<Panel class="PremiumProgressContainer" >
										<Label text="#DOTA_BattlePassPostGame_EventGameTI10_WeeklyPremiumProgress" class="WeeklyPremiumProgressLabel" />
										<Label text="+{d:weekly_premium_progress}" class="WeeklyPremiumProgressLabel PremiumProgress"/>					
									</Panel>
								</Panel>
								<Panel class="EventGame_Progress">
									<Label text="#DOTA_BattlePassPostGame_EventGameTI10_WeeklyCap" class="EventGame_Progress_Cap" />
									<ProgressBarWithMiddle id="EventGameWeeklyProgress" class="EventGame_Progress_Bar" />
									<Label text="#DOTA_BattlePassPostGame_EventGameTI10_WeeklyProgress" class="WeeklyChallengeProgressLabel" html="true"/>
								</Panel>
									
							</Panel>
							<Panel id="XPCircleContainer" />
						</Panel>
						
						<Panel id="BattlePassCavernCrawlProgress" class="BattlePassProgressTypeContainer">
							<Panel class="CavernCrawlTitleContainer">
								<Panel class="CavernCrawlLogo" />
								<Label class="ProgressTypeTitle" text="#DOTA_BattlePassPostGame_CavernCrawlProgress" />
							</Panel>
							<Panel class="BattlePassProgressTypeDetails">
								<Panel class="CavernCrawlMap">
									<Panel class="MapImage" />
									<DOTAHeroMovie id="CavernCrawlHero" class="BattlePassProgressHeroMovie" scaling="none" />
								</Panel>
								<Panel class="ProgressCompletedContainer">
									<Label class="ProgressCompleted" text="#DOTA_BattlePassPostGame_Complete" />
								</Panel>
							</Panel>
							<Panel id="XPCircleContainer" />
						</Panel>

						<Panel id="BattlePassWagerProgress" class="BattlePassProgressTypeContainer" >
							<Label class="ProgressTypeTitle" text="#DOTA_BattlePassPostGame_WagerProgress" />
							<Panel class="BattlePassProgressTypeDetails">
								<Panel class="WagerContainer Wager" >
									<Panel>
										<Panel class="WagerToken"/>
										<Label class="TeamWagerTokenLabel" text="{i:wager_amount}"/>
									</Panel>
									<Label class="TeamWagerTokenCount" text="#DOTA_BattlePassPostGame_WagerConversion"/>
								</Panel>
								<Panel class="WagerContainer TeamWagerBonus" >
									<Panel class="TeamWagerBonuses">
										<Label class="TeamWagerBonusLabel" text="#DOTA_BattlePassPostGame_WagerTeamBonus"/>
									</Panel>
								</Panel>
							</Panel>
							<Panel id="XPCircleContainer" />
						</Panel>

						<Panel id="BattlePassTipsProgress" class="BattlePassProgressTypeContainer">
							<Label class="ProgressTypeTitle" text="#DOTA_BattlePassPostGame_TipProgress" />
							<Panel class="BattlePassProgressTypeDetails">
								<Panel class="TotalTipContainer">
									<Panel class="TipToken"	/>
									<Label class="TotalTipCount" text="x {i:total_tip_count}"/>
								</Panel>
								<Panel class="TipBottomSection">
									<Panel class="TipListContainer">
										<Panel id="TipContainer">
											<!-- Filled in by js -->
										</Panel>
										<Panel id="TipContainer2">
											<!-- Filled in by js -->
										</Panel>								
									</Panel>									
								</Panel>
							</Panel>
							<Panel id="XPCircleContainer" />
						</Panel>
						
						<Panel id="BattlePassActionsGrantedProgress" class="BattlePassProgressTypeContainer">
							<Label class="ProgressTypeTitle" text="#DOTA_BattlePassPostGame_ActionProgress" />
							<Panel class="BattlePassProgressTypeDetails">
								<Panel class="ActionOuterContainer">
									<Panel id="ActionContainer">
											<!-- Filled in by js -->					
									</Panel>									
								</Panel>
							</Panel>
							<Panel id="XPCircleContainer" />
						</Panel>
						

						<Panel id="BattlePassDailyChallengeProgress" class="BattlePassProgressTypeContainer">
							<Label class="ProgressTypeTitle" text="#DOTA_BattlePassPostGame_DailyChallengeProgress" />
							<Panel class="BattlePassProgressTypeDetails">
								<DOTAHeroMovie id="DailyChallengeHeroMovie" class="BattlePassProgressHeroMovie" scaling="none" />
								<Panel class="ProgressCompletedContainer">
									<Label class="ProgressCompleted" text="#DOTA_BattlePassPostGame_Complete" />
								</Panel>
							</Panel>
							<Panel id="XPCircleContainer" />
						</Panel>

						<Panel id="BattlePassWeeklyChallengeProgress" class="BattlePassProgressTypeContainer">
							<Label class="ProgressTypeTitle" text="#DOTA_BattlePassPostGame_WeeklyChallengeProgress" />
							<Panel class="BattlePassProgressTypeDetails">
								<Panel class="WeeklyChallengeContainer">
									<Panel class="WeeklyChallengeInfo">
										<Label class="WeeklyChallengeDesc" text="#DOTA_Challenge_MultiGame"/>
										<Label class="WeeklyChallengeDesc" text="{s:weekly_challenge_description}" html="true" />
										<ProgressBarWithMiddle id="WeeklyChallengeProgress" class="WeeklyChallengeProgress"/>
										<Label text="#DOTA_BattlePassPostGame_WeeklyChallenge_Progress" class="WeeklyChallengeProgressLabel" html="true"/>
										<Panel class="WeeklyChallengeIncrementGlowContainer">
											<Label class="WeeklyChallengeIncrementText Glow" text="#DOTA_BattlePassPostGame_WeeklyChallenge_Increment" />
											<Label class="WeeklyChallengeIncrementText" text="#DOTA_BattlePassPostGame_WeeklyChallenge_Increment" />
										</Panel>
									</Panel>
								</Panel>
								<Panel class="ProgressCompletedContainer">
									<Label class="ProgressCompleted Glow" text="#DOTA_BattlePassPostGame_Complete" />
									<Label class="ProgressCompleted" text="#DOTA_BattlePassPostGame_Complete" />
								</Panel>
							</Panel>
							<Panel id="XPCircleContainer" />
						</Panel>

						<Panel id="BattlePassGuildProgress" class="BattlePassProgressTypeContainer">
							<Label class="ProgressTypeTitle" text="#DOTA_BattlePassPostGame_GuildProgress" />
							<Panel class="BattlePassProgressTypeDetails">
								<Panel id="GuildContracts" class="GuildSection">
									<Label class="GuildSectionTitle" text="#DOTA_BattlePassPostGame_GuildContracts" />
									<Panel id="GuildContractList" />
								</Panel>
								<Panel id="GuildChallenge" class="GuildSection">
									<Label class="GuildSectionTitle" text="#DOTA_BattlePassPostGame_GuildChallenge" />
									<Panel id="GuildChallengeDetails">
										<Image id="GuildChallengeImage" />
										<Panel id="GuildChallengeProgressContainer">
											<ProgressBarWithMiddle id="GuildChallengeProgressBar" />
											<Label id="GuildChallengeProgress" text="{d:challenge_start_value}/{d:challenge_max_value} &lt;span class=&quot;ChallengeProgress&quot;&gt;+{d:challenge_progress}&lt;/span&gt;" html="true"/>
										</Panel>
									</Panel>
								</Panel>
								
							</Panel>
							<Panel id="XPCircleContainer" />
						</Panel>
					</Panel>

					<Panel id="BattlePassProgressCenter">
						<Panel class="BattlePassProgressBarTop">
							<DOTAEventLevelShield id="BattlePassLevelShield" />
							<Panel class="BattlePassPointsTotalContainer">
								<Label class="BattlePassPointsTotalTitle" text="#DOTA_BattlePassPostGame_Total" />
								<Panel class="BattlePassPointsTotalGlowContainer">
									<Label class="BattlePassPointsTotal" text="+{d:total_points_gained}" />
								</Panel>
							</Panel>
						</Panel>

						<Panel id="BattleLevelProgressContainer">
							<Panel class="ProgressBarContainer" >
								<ProgressBarWithMiddle id="BattleLevelProgress" min="0" max="1000" />
								<Panel id="BattleLevelProgressSection">
									<Label class="BattlePassProgressLevelProgressTitle" text="#DOTA_BattlePassPostGame_LevelProgress" />
									<Label class="BattlePassLevelProgressBP" text="#DOTA_BattlePass_BPProgress" />
								</Panel>
							</Panel>
						</Panel>
					</Panel>
				</Panel>

			</Panel>
		</snippet>

		<!-- Cavern Crawl Progress -->
		
		<snippet name="CavernCrawlProgress">
			<Panel class="ProgressScreen" onactivate="StartSkippingAhead()" >
				<DOTACavernCrawlPostGameProgress id="CavernCrawl" />
			</Panel>
		</snippet>


		<!-- Generic Arcana Progress -->
		<snippet name="GenericArcanaProgress">
			<Panel class="ProgressScreen" onactivate="StartSkippingAhead()">
				<Panel class="GenericArcanaBackground" />
				<Panel id="GenericArcanaProgressMain">
					<DOTAScenePanel id="GenericArcanaModelUnstyled" particleonly="false" antialias="true" yawmin="-45" yawmax="-45" />
					<DOTAScenePanel id="GenericArcanaModel" particleonly="false" antialias="true" />
					<Panel class="GenericArcanaData">
						<Label id="GenericArcanaHeader" html="true" text="{s:arcana_progress_header}"/>
						<Label id="GenericArcanaProgressTitle" html="true" text="{s:arcana_progress_title}"/>
						<Panel class="GenericArcanaDataContainer">
							<Panel id="GenericArcanaProgressBarContainer">
								<Panel id="GenericArcanaHeroIcon"/>
								<ProgressBar id="GenericArcanaProgressBar" min="0" max="1000">
									<Label id="GenericArcanaProgressBarLabel" html="true" text="{s:arcana_progress_bar}"/>
								</ProgressBar>
							</Panel>
							<Panel id="GenericArcanaDataSeparator"/>
							<Panel class="GenericArcanaProgressLower">
								<Label id="GenericArcanaProgressDescription" html="true" text="{s:arcana_progress_description}"/>
								<Label id="GenericArcanaProgressIncrement" html="true" text="{s:arcana_progress_increment}"/>
							</Panel>
						</Panel>
					</Panel>
				</Panel>
			</Panel>
		</snippet>
		
		<!-- Rubick Arcana Progress -->
		<snippet name="RubickArcanaProgress">
			<Panel class="ProgressScreen" onactivate="StartSkippingAhead()">

				<Panel class="RubickArcanaBackground" />

				<Panel id="RubickArcanaProgressMain">
					<DOTAScenePanel id="RubickArcanaModel" unit="npc_dota_hero_rubick" particleonly="false" antialias="true" />
					<DOTARubickArcanaProgress id="RubickArcanaProgress" />
				</Panel>
			</Panel>
		</snippet>
		

		<!-- Wraith King Arcana Progress -->

		<snippet name="WraithKingArcanaProgress">
			<Panel class="ProgressScreen" >
				<DOTAWraithKingArcanaPostGameProgress id="WraithKingArcanaProgress" />
			</Panel>
		</snippet>
		
		<snippet name="MVP2MapRadiant">
			<Panel>
					<DOTAScenePanel 
						id="MVPMap" 
						map="scenes/mvp/mvp_ti10_radiant" 
						light="versus_light" 
						deferredalpha ="false"
						renderdeferred="true"
						particleonly="false" 
						/>
			</Panel>
		</snippet>
		<snippet name="MVP2MapDire">
			<Panel>
					<DOTAScenePanel 
						id="MVPMap" 
						map="scenes/mvp/mvp_ti10_dire"
						light="versus_light" 
						deferredalpha ="false"
						renderdeferred="true"
						particleonly="false" 
						/>
			</Panel>
		</snippet>

		<snippet name="MVP2Screen">
			<Panel class="ProgressScreen" onactivate="StartSkippingAhead()">
				<Panel id="MVPMapContainer" />
			
				<DOTAScenePanel id="MVPModel" particleonly="false" antialias="true"/>
				<Panel id="MVPDetails">
					<Panel id="MatchMVPCrown" />
					<Label class="MatchMVPText" text="#DOTAMVPVote_Title"/>
					<Label class="Username"		hittest="false" html="true" text="{g:dota_persona:ng:user_account_id}"/>
					<Label class="Hero" text="{s:hero}"/>
					<Panel id="GuildDetails" class="GuildDetails">
						<DOTAGuildImage id="GuildImage" class="GuildImage" />
						<Label class="Guildtag"		hittest="false" html="true" text="[{g:dota_guild_tag:user_guild_id}]"/>
						<Label class="Guildname"	hittest="false" html="true" text="{g:dota_guild_name:user_guild_id}"/>
					</Panel>
					<Panel class="Accolades" id="Accolades"/>
				</Panel>
			
				<Panel id="HonorableMentionsContainer">
					<Label text="#DOTA_MVP_HonorableMentions" />
					<Panel id="HonorableMentions"/>
				</Panel>
			</Panel>
		</snippet>

		<snippet name="EventPointsProgress" >
			<Panel class="ProgressScreen" onactivate="StartSkippingAhead()" >

				<Panel class="EventPointsBackground">
					<Panel class="EventPointsBackgroundImage" />
				</Panel>

				<Panel id="EventPointsProgressMain" hittest="false">

					<DOTAEventLevelShield id="EventPointsLevelShield" />

					<Panel id="EventPointsProgressCenter">
						<Panel class="EventPointsProgressTitle">
							<Panel class="EventPointsProgressTitleGlowContainer">
								<Label class="EventPointsProgressTitleText Glow" text="#DOTA_EventPointsPostGame_Progress" />
								<Label class="EventPointsProgressTitleText" text="#DOTA_EventPointsPostGame_Progress" />
							</Panel>
						</Panel>

						<Panel id="EventPointsLevelProgressContainer">
							<Panel class="EventPointsShieldSpacer" />
							<Panel class="ProgressBarContainer" >
								<ProgressBarWithMiddle id="BattleLevelProgress" min="0" max="1000" />
								<Panel id="EventPointsLevelProgressSection">
									<Label class="EventPointsProgressLevelProgressTitle" text="#DOTA_BattlePassPostGame_LevelProgress" />
									<Label class="EventPointsLevelProgressBP" text="#DOTA_BattlePass_BPProgress" />
								</Panel>
							</Panel>
							<Panel class="EventPointsPointsTotalContainer">
								<Label class="EventPointsPointsTotalTitle" text="#DOTA_BattlePassPostGame_Total" />
								<Panel class="EventPointsPointsTotalGlowContainer">
									<Label class="EventPointsPointsTotal Glow" text="+{d:total_points_gained}" />
									<Label class="EventPointsPointsTotal" text="+{d:total_points_gained}" />
								</Panel>
							</Panel>
						</Panel>
					</Panel>
					
					<Panel id="EventPointsProgressCore">
						<Panel id="EventPointsProgressBPGrid">
							<Panel id="EventPointsProgressRows">
								<Panel id="EventPointsWonGameRow" class="EventPointsProgressRow">
									<Label class="EventPointsProgressRowType" text="#DOTA_EventPointsPostGame_WonGame" />
									<Label class="EventPointsProgressRowValue" text="{d:total_points_gained}" />
								</Panel>
							</Panel>
							<!--<Panel id="EventPointsTotalsRow" class="EventPointsProgressRow">
								<Label class="EventPointsProgressRowType" text="#DOTA_BattlePassPostGame_Total" />
								<Label class="EventPointsProgressRowValue" text="#DOTA_BattlePassPostGame_BPValue" />
							</Panel>-->
						</Panel>
					</Panel>
				</Panel>
				
			</Panel>
		</snippet>
		
		<snippet name="Frostivus2018Progress" >
			<Panel class="ProgressScreen" onactivate="StartSkippingAhead()" >

				<Panel class="Frostivus2018Background">
					<Panel class="Frostivus2018BackgroundImage" />					
				</Panel>

				<Panel id="Frostivus2018ProgressMain" hittest="false">

					<DOTAEventLevelShield id="Frostivus2018LevelShield" />

					<Panel id="Frostivus2018ProgressCenter">
						<Panel class="Frostivus2018ProgressTitle">
							<Panel class="Frostivus2018ProgressTitleGlowContainer">
								<Label class="Frostivus2018ProgressTitleText Glow" text="#DOTA_Frostivus2018PostGame_Progress" />
								<Label class="Frostivus2018ProgressTitleText" text="#DOTA_Frostivus2018PostGame_Progress" />
							</Panel>
						</Panel>

						<Panel id="Frostivus2018LevelProgressContainer">
							<Panel class="Frostivus2018ShieldSpacer" />
							<Panel class="ProgressBarContainer" >
								<ProgressBarWithMiddle id="BattleLevelProgress" min="0" max="1000" />
								<Panel id="Frostivus2018LevelProgressSection">
									<Label class="Frostivus2018ProgressLevelProgressTitle" text="#DOTA_BattlePassPostGame_LevelProgress" />
									<Label class="Frostivus2018LevelProgressBP" text="#DOTA_BattlePass_BPProgress" />
								</Panel>
							</Panel>
							<Panel class="Frostivus2018PointsTotalContainer">
								<Label class="Frostivus2018PointsTotalTitle" text="#DOTA_BattlePassPostGame_Total" />
								<Panel class="Frostivus2018PointsTotalGlowContainer">
									<Label class="Frostivus2018PointsTotal Glow" text="+{d:total_points_gained}" />
									<Label class="Frostivus2018PointsTotal" text="+{d:total_points_gained}" />
								</Panel>
							</Panel>
						</Panel>
					</Panel>
					
					<Panel id="Frostivus2018ProgressCore">
						<Panel id="Frostivus2018ProgressBPGrid">
							<!--<Panel id="Frostivus2018ProgressRows">
							</Panel>
							<Panel id="Frostivus2018TotalsRow" class="Frostivus2018ProgressRow">
								<Label class="Frostivus2018ProgressRowType" text="#DOTA_BattlePassPostGame_Total" />
								<Label class="Frostivus2018ProgressRowValue" text="#DOTA_BattlePassPostGame_BPValue" />
							</Panel>-->
						</Panel>
					</Panel>
				</Panel>
				
			</Panel>
		</snippet>

		<snippet name="CoachRating">
			<Panel class="ProgressScreen CoachRating">
				<Panel class="CoachRatingMain">
					<Panel class="CoachRatingBackground" />
					<Panel class="CoachRatingContents">
						<Label class="CoachRatingTitle" text="#DOTA_CoachRating" />
						<Label class="CoachRatingQuestion" text="#DOTA_CoachRating_Experience" />
						<Panel class="CoachDetails">
							<DOTACoachRatingBadge id="CoachRatingBadge" />
							<DOTAAvatarImage id="CoachAvatarImage" />
							<Panel class="CoachInfo">
								<Label class="CoachUserName" text="{s:coach_player_name}" />
								<Label class="CoachSubtitle" text="#DOTA_Coach" />
							</Panel>
							<Panel class="FillWidth" />
							<Label class="CoachTimeRemaining" text="#DOTA_Trivia_TimeRemaining" />
							<Panel class="CoachTimeRemainingProgress">
								<CircularProgressBar id="CoachTimeRemainingProgressBar" />
								<Panel class="CoachTimeRemainingProgressBarOverlay" />
								<Label class="CoachTimeRemainingProgressText" text="{d:countdown_seconds}" />
							</Panel>
						</Panel>
						<Panel class="CoachRatingButtons">
							<Button id="GoodRatingButton" class="CoachRatingButton">
								<Panel class="CoachRatingButtonIcon" />
								<Panel class="CoachRatingButtonText">
									<Label class="CoachRatingButtonTitle" text="#DOTA_CoachRating_Good_Title" />
									<Label class="CoachRatingButtonSubtitle" text="#DOTA_CoachRating_Good_Desc" />
								</Panel>
							</Button>
							<Button id="BadRatingButton" class="CoachRatingButton">
								<Panel class="CoachRatingButtonIcon" />
								<Panel class="CoachRatingButtonText">
									<Label class="CoachRatingButtonTitle" text="#DOTA_CoachRating_Bad_Title" />
									<Label class="CoachRatingButtonSubtitle" text="#DOTA_CoachRating_Bad_Desc" />
								</Panel>
							</Button>
						</Panel>
						<Button id="AbusiveRatingButton">
							<Panel class="AbusiveRatingButtonCenter">
								<Panel class="AbusiveRatingButtonIcon" />
								<Label text="#DOTA_CoachRating_Report" />
							</Panel>
						</Button>
					</Panel>
				</Panel>
			</Panel>
		</snippet>

		<snippet name="PlayerMatchSurvey">
			<Panel class="ProgressScreen PlayerMatchSurvey">
				<Panel class="PlayerMatchSurveyMain">
					<Panel class="PlayerMatchSurveyBackground" />
					<Panel class="PlayerMatchSurveyContents">
						<Label class="PlayerMatchSurveyTitle" text="#DOTA_PlayerMatchSurvey_Title" />
						<Label class="PlayerMatchSurveyQuestion" text="#DOTA_PlayerMatchSurvey_Desc" />

						<!-- Look for flag values in EPlayerMatchSurveyFlag  -->
						<Panel class="PlayerMatchSurveyButtons">
							<Panel id="GoodRatingContainer" class="PlayerMatchSurveyRatingContainer">
								<Panel class="PopupButton PlayerMatchSurveyHeader">
									<Panel class="PositiveIcon" />
									<Label class="" text="#DOTA_PlayerMatchSurvey_Positive_Title" />
								</Panel>
								<TextButton class="PopupButton PlayerMatchSurveyButton Positive" text="#DOTA_PlayerMatchSurvey_Positive_Teamwork" rating_flag="1"/>
								<TextButton class="PopupButton PlayerMatchSurveyButton Positive" text="#DOTA_PlayerMatchSurvey_Positive_MatchBalance" rating_flag="2"/>
								<TextButton class="PopupButton PlayerMatchSurveyButton Positive" text="#DOTA_PlayerMatchSurvey_Positive_TeamBehavior" rating_flag="3"/>
								<TextButton class="PopupButton PlayerMatchSurveyButton Positive" text="#DOTA_PlayerMatchSurvey_Positive_IndividualPerformance" rating_flag="4"/>
								<TextButton class="PopupButton PlayerMatchSurveyButton Positive" text="#DOTA_PlayerMatchSurvey_Positive_HeroChoice" rating_flag="5"/>
								<TextButton class="PopupButton PlayerMatchSurveyButton Positive" text="#DOTA_PlayerMatchSurvey_Positive_Comeback" rating_flag="6"/>
							</Panel>

							<Panel id="BadRatingContainer" class="PlayerMatchSurveyRatingContainer">
								<Panel class="PopupButton PlayerMatchSurveyHeader">
									<Panel class="NegativeIcon" />
									<Label class="" text="#DOTA_PlayerMatchSurvey_Negative_Title" />
								</Panel>
								<TextButton class="PopupButton PlayerMatchSurveyButton Negative" text="#DOTA_PlayerMatchSurvey_Negative_Teamwork" rating_flag="1"/>
								<TextButton class="PopupButton PlayerMatchSurveyButton Negative" text="#DOTA_PlayerMatchSurvey_Negative_MatchBalance" rating_flag="2"/>
								<TextButton class="PopupButton PlayerMatchSurveyButton Negative" text="#DOTA_PlayerMatchSurvey_Negative_TeamBehavior" rating_flag="3"/>
								<TextButton class="PopupButton PlayerMatchSurveyButton Negative" text="#DOTA_PlayerMatchSurvey_Negative_IndividualPerformance" rating_flag="4"/>
								<TextButton class="PopupButton PlayerMatchSurveyButton Negative" text="#DOTA_PlayerMatchSurvey_Negative_HeroChoice" rating_flag="5"/>
								<TextButton class="PopupButton PlayerMatchSurveyButton Negative" text="#DOTA_PlayerMatchSurvey_Negative_Smurf" rating_flag="7"/>
							</Panel>
						</Panel>

						<Panel class="PlayerMatchSurveyFooter">
							<Button id="SkipButton">
								<Panel class="SkipButtonCenter">
									<Label text="#DOTA_PlayerMatchSurvey_Skip" />
								</Panel>
							</Button>

							<Label class="PlayerMatchSurveySubmitted" text="#DOTA_PlayerMatchSurvey_Submitted" />
						</Panel>
					</Panel>
				</Panel>
			</Panel>
		</snippet>	
	</snippets>

	<DOTAPostGameProgress hittest="false">
		<Panel id="ProgressScreens" hittest="false" />
		<Panel id="DebugControls">
			<TextButton class="PopupButton" text="MVP 2.0" onactivate="TestMVP2Screen()" />
			<TextButton class="PopupButton" text="MVP Voting" onactivate="TestMVPVotingProgress()" />
			<TextButton class="PopupButton" text="Player Match Survey" onactivate="TestAnimatePlayerMatchSurvey()" />
			<TextButton class="PopupButton" text="Coach Rating" onactivate="TestAnimateCoachRating()" />
			<TextButton class="PopupButton" text="Hero Badge" onactivate="TestAnimateHeroBadgeLevel()" />
			<TextButton class="PopupButton" text="Match Rewards" onactivate="TestAnimateMatchRewards()" />
			<TextButton class="PopupButton" text="Hero Relics" onactivate="TestAnimateHeroRelics()" />
			<TextButton class="PopupButton" text="Gauntlet Progress" onactivate="TestAnimateGauntletProgress()" />
			<TextButton class="PopupButton" text="Spring 2021 Points" onactivate="TestAnimateSpring2021()" />
			<TextButton class="PopupButton" text="Battle Points" onactivate="TestAnimateBattlePass()" />
			<TextButton class="PopupButton" text="Cavern" onactivate="TestAnimateCavernCrawl()" />
			<TextButton class="PopupButton" text="Rubick Arcana" onactivate="TestAnimateRubickArcanaProgress()" />
			<TextButton class="PopupButton" text="WK Arcana" onactivate="TestAnimateWraithKingArcanaProgress()" />
			<TextButton class="PopupButton" text="Frostivus" onactivate="TestAnimateFrostivusProgress()" />
			<TextButton class="PopupButton" text="Event Points" onactivate="TestAnimateEventPointsProgress()" />
			<TextButton class="PopupButton" text="Diretide 2020" onactivate="TestAnimateDiretideProgress()" />
			<TextButton class="PopupButton Blue" text="Reset" onactivate="ResetScreens()" />
			<TextButton class="PopupButton Blue" text="Hide" onactivate="HideProgress()" />
		</Panel>

	</DOTAPostGameProgress>

</root>
